{
	"title": "net.minecraft.network.protocol.game.ClientboundAddEntityPacket",
	"items": [
		{
			"forge": "net.minecraft.network.protocol.game.ClientboundAddEntityPacket",
			"fabric": "net.minecraft.network.packet.s2c.play.EntitySpawnS2CPacket"
		},
		{
			"forge": "MAGICAL_QUANTIZATION",
			"fabric": "VELOCITY_SCALE"
		},
		{
			"forge": "MAGICAL_QUANTIZATION",
			"fabric": "VELOCITY_SCALE"
		},
		{
			"forge": "LIMIT",
			"fabric": "MAX_ABSOLUTE_VELOCITY"
		},
		{
			"forge": "id",
			"fabric": "id"
		},
		{
			"forge": "uuid",
			"fabric": "uuid"
		},
		{
			"forge": "type",
			"fabric": "entityType"
		},
		{
			"forge": "x",
			"fabric": "x"
		},
		{
			"forge": "y",
			"fabric": "y"
		},
		{
			"forge": "z",
			"fabric": "z"
		},
		{
			"forge": "xa",
			"fabric": "velocityX"
		},
		{
			"forge": "ya",
			"fabric": "velocityY"
		},
		{
			"forge": "za",
			"fabric": "velocityZ"
		},
		{
			"forge": "xRot",
			"fabric": "pitch"
		},
		{
			"forge": "yRot",
			"fabric": "yaw"
		},
		{
			"forge": "yHeadRot",
			"fabric": "headYaw"
		},
		{
			"forge": "data",
			"fabric": "entityData"
		},
		{
			"forge": "write(FriendlyByteBuf arg0)",
			"fabric": "write(PacketByteBuf arg0)"
		},
		{
			"forge": "write(FriendlyByteBuf arg0)",
			"fabric": "write(PacketByteBuf arg0)"
		},
		{
			"forge": "handle(ClientGamePacketListener arg0)",
			"fabric": "apply(ClientPlayPacketListener arg0)"
		},
		{
			"forge": "getId()",
			"fabric": "getId()"
		},
		{
			"forge": "getUUID()",
			"fabric": "getUuid()"
		},
		{
			"forge": "getType()",
			"fabric": "getEntityType()"
		},
		{
			"forge": "getX()",
			"fabric": "getX()"
		},
		{
			"forge": "getY()",
			"fabric": "getY()"
		},
		{
			"forge": "getZ()",
			"fabric": "getZ()"
		},
		{
			"forge": "getXa()",
			"fabric": "getVelocityX()"
		},
		{
			"forge": "getYa()",
			"fabric": "getVelocityY()"
		},
		{
			"forge": "getZa()",
			"fabric": "getVelocityZ()"
		},
		{
			"forge": "getXRot()",
			"fabric": "getPitch()"
		},
		{
			"forge": "getYRot()",
			"fabric": "getYaw()"
		},
		{
			"forge": "getYHeadRot()",
			"fabric": "getHeadYaw()"
		},
		{
			"forge": "getData()",
			"fabric": "getEntityData()"
		}
	]
}