{
	"title": "net.minecraft.world.level.block.FletchingTableBlock",
	"items": [
		{
			"forge": "net.minecraft.world.level.block.FletchingTableBlock",
			"fabric": "net.minecraft.block.FletchingTableBlock"
		},
		{
			"forge": "use(BlockState arg0, Level arg1, BlockPos arg2, Player arg3, InteractionHand arg4, BlockHitResult arg5)",
			"fabric": "onUse(BlockState arg0, World arg1, BlockPos arg2, PlayerEntity arg3, Hand arg4, BlockHitResult arg5)"
		},
		{
			"forge": "use(BlockState arg0, Level arg1, BlockPos arg2, Player arg3, InteractionHand arg4, BlockHitResult arg5)",
			"fabric": "onUse(BlockState arg0, World arg1, BlockPos arg2, PlayerEntity arg3, Hand arg4, BlockHitResult arg5)"
		}
	]
}