{
	"title": "net.minecraft.client.resources.metadata.texture.TextureMetadataSection",
	"items": [
		{
			"forge": "net.minecraft.client.resources.metadata.texture.TextureMetadataSection",
			"fabric": "net.minecraft.client.resource.metadata.TextureResourceMetadata"
		},
		{
			"forge": "SERIALIZER",
			"fabric": "READER"
		},
		{
			"forge": "SERIALIZER",
			"fabric": "READER"
		},
		{
			"forge": "DEFAULT_BLUR",
			"fabric": "field_32980"
		},
		{
			"forge": "DEFAULT_CLAMP",
			"fabric": "field_32981"
		},
		{
			"forge": "blur",
			"fabric": "blur"
		},
		{
			"forge": "clamp",
			"fabric": "clamp"
		},
		{
			"forge": "isBlur()",
			"fabric": "shouldBlur()"
		},
		{
			"forge": "isBlur()",
			"fabric": "shouldBlur()"
		},
		{
			"forge": "isClamp()",
			"fabric": "shouldClamp()"
		}
	]
}