{
	"title": "net.minecraft.world.level.block.KelpPlantBlock",
	"items": [
		{
			"forge": "net.minecraft.world.level.block.KelpPlantBlock",
			"fabric": "net.minecraft.block.KelpPlantBlock"
		},
		{
			"forge": "getHeadBlock()",
			"fabric": "getStem()"
		},
		{
			"forge": "getHeadBlock()",
			"fabric": "getStem()"
		},
		{
			"forge": "getFluidState(BlockState arg0)",
			"fabric": "getFluidState(BlockState arg0)"
		},
		{
			"forge": "canAttachTo(BlockState arg0)",
			"fabric": "canAttachTo(BlockState arg0)"
		},
		{
			"forge": "canPlaceLiquid(BlockGetter arg0, BlockPos arg1, BlockState arg2, Fluid arg3)",
			"fabric": "canFillWithFluid(BlockView arg0, BlockPos arg1, BlockState arg2, Fluid arg3)"
		},
		{
			"forge": "placeLiquid(LevelAccessor arg0, BlockPos arg1, BlockState arg2, FluidState arg3)",
			"fabric": "tryFillWithFluid(WorldAccess arg0, BlockPos arg1, BlockState arg2, FluidState arg3)"
		}
	]
}