{
	"title": "net.minecraft.util.eventlog.EventLogDirectory$FileId",
	"items": [
		{
			"forge": "net.minecraft.util.eventlog.EventLogDirectory$FileId",
			"fabric": "net.minecraft.util.logging.LogFileCompressor$LogId"
		},
		{
			"forge": "date",
			"fabric": "date"
		},
		{
			"forge": "date",
			"fabric": "date"
		},
		{
			"forge": "index",
			"fabric": "index"
		},
		{
			"forge": "DATE_FORMATTER",
			"fabric": "DATE_TIME_FORMATTER"
		},
		{
			"forge": "parse(String arg0)",
			"fabric": "fromFileName(String fileName)"
		},
		{
			"forge": "parse(String arg0)",
			"fabric": "fromFileName(String fileName)"
		},
		{
			"forge": "toFileName(String arg0)",
			"fabric": "getFileName(String extension)"
		},
		{
			"forge": "date()",
			"fabric": "date()"
		},
		{
			"forge": "index()",
			"fabric": "index()"
		}
	]
}