{
	"title": "net.minecraft.client.gui.screens.social.PlayerSocialManager",
	"items": [
		{
			"forge": "net.minecraft.client.gui.screens.social.PlayerSocialManager",
			"fabric": "net.minecraft.client.network.SocialInteractionsManager"
		},
		{
			"forge": "minecraft",
			"fabric": "client"
		},
		{
			"forge": "minecraft",
			"fabric": "client"
		},
		{
			"forge": "hiddenPlayers",
			"fabric": "hiddenPlayers"
		},
		{
			"forge": "service",
			"fabric": "userApiService"
		},
		{
			"forge": "discoveredNamesToUUID",
			"fabric": "playerNameByUuid"
		},
		{
			"forge": "onlineMode",
			"fabric": "blockListLoaded"
		},
		{
			"forge": "pendingBlockListRefresh",
			"fabric": "blockListLoader"
		},
		{
			"forge": "hidePlayer(UUID arg0)",
			"fabric": "hidePlayer(UUID uuid)"
		},
		{
			"forge": "hidePlayer(UUID arg0)",
			"fabric": "hidePlayer(UUID uuid)"
		},
		{
			"forge": "showPlayer(UUID arg0)",
			"fabric": "showPlayer(UUID uuid)"
		},
		{
			"forge": "shouldHideMessageFrom(UUID arg0)",
			"fabric": "isPlayerMuted(UUID uuid)"
		},
		{
			"forge": "isHidden(UUID arg0)",
			"fabric": "isPlayerHidden(UUID uuid)"
		},
		{
			"forge": "startOnlineMode()",
			"fabric": "loadBlockList()"
		},
		{
			"forge": "stopOnlineMode()",
			"fabric": "unloadBlockList()"
		},
		{
			"forge": "isBlocked(UUID arg0)",
			"fabric": "isPlayerBlocked(UUID uuid)"
		},
		{
			"forge": "getHiddenPlayers()",
			"fabric": "getHiddenPlayers()"
		},
		{
			"forge": "getDiscoveredUUID(String arg0)",
			"fabric": "getUuid(String playerName)"
		},
		{
			"forge": "addPlayer(PlayerInfo arg0)",
			"fabric": "setPlayerOnline(PlayerListEntry player)"
		},
		{
			"forge": "removePlayer(UUID arg0)",
			"fabric": "setPlayerOffline(UUID uuid)"
		}
	]
}