{
	"title": "net.minecraft.world.level.block.entity.HangingSignBlockEntity",
	"items": [
		{
			"forge": "net.minecraft.world.level.block.entity.HangingSignBlockEntity",
			"fabric": "net.minecraft.block.entity.HangingSignBlockEntity"
		},
		{
			"forge": "MAX_TEXT_LINE_WIDTH",
			"fabric": "MAX_TEXT_WIDTH"
		},
		{
			"forge": "MAX_TEXT_LINE_WIDTH",
			"fabric": "MAX_TEXT_WIDTH"
		},
		{
			"forge": "TEXT_LINE_HEIGHT",
			"fabric": "TEXT_LINE_HEIGHT"
		},
		{
			"forge": "getTextLineHeight()",
			"fabric": "getTextLineHeight()"
		},
		{
			"forge": "getTextLineHeight()",
			"fabric": "getTextLineHeight()"
		},
		{
			"forge": "getMaxTextLineWidth()",
			"fabric": "getMaxTextWidth()"
		}
	]
}