{
	"title": "net.minecraft.world.level.levelgen.structure.structures.WoodlandMansionStructure",
	"items": [
		{
			"forge": "net.minecraft.world.level.levelgen.structure.structures.WoodlandMansionStructure",
			"fabric": "net.minecraft.world.gen.structure.WoodlandMansionStructure"
		},
		{
			"forge": "CODEC",
			"fabric": "CODEC"
		},
		{
			"forge": "CODEC",
			"fabric": "CODEC"
		},
		{
			"forge": "findGenerationPoint(Structure$GenerationContext arg0)",
			"fabric": "getStructurePosition(Structure$Context arg0)"
		},
		{
			"forge": "findGenerationPoint(Structure$GenerationContext arg0)",
			"fabric": "getStructurePosition(Structure$Context arg0)"
		},
		{
			"forge": "generatePieces(StructurePiecesBuilder arg0, Structure$GenerationContext arg1, BlockPos arg2, Rotation arg3)",
			"fabric": "addPieces(StructurePiecesCollector collector, Structure$Context context, BlockPos pos, BlockRotation rotation)"
		},
		{
			"forge": "afterPlace(WorldGenLevel arg0, StructureManager arg1, ChunkGenerator arg2, RandomSource arg3, BoundingBox arg4, ChunkPos arg5, PiecesContainer arg6)",
			"fabric": "postPlace(StructureWorldAccess arg0, StructureAccessor arg1, ChunkGenerator arg2, Random arg3, BlockBox arg4, ChunkPos arg5, StructurePiecesList arg6)"
		},
		{
			"forge": "type()",
			"fabric": "getType()"
		}
	]
}