{
	"title": "net.minecraft.world.level.NaturalSpawner$SpawnPredicate",
	"items": [
		{
			"forge": "net.minecraft.world.level.NaturalSpawner$SpawnPredicate",
			"fabric": "net.minecraft.world.SpawnHelper$Checker"
		},
		{
			"forge": "test(EntityType<?> arg0, BlockPos arg1, ChunkAccess arg2)",
			"fabric": "test(EntityType<?> type, BlockPos pos, Chunk chunk)"
		},
		{
			"forge": "test(EntityType<?> arg0, BlockPos arg1, ChunkAccess arg2)",
			"fabric": "test(EntityType<?> type, BlockPos pos, Chunk chunk)"
		}
	]
}