{
	"title": "net.minecraft.world.damagesource.DeathMessageType",
	"items": [
		{
			"forge": "net.minecraft.world.damagesource.DeathMessageType",
			"fabric": "net.minecraft.entity.damage.DeathMessageType"
		},
		{
			"forge": "DEFAULT",
			"fabric": "DEFAULT"
		},
		{
			"forge": "DEFAULT",
			"fabric": "DEFAULT"
		},
		{
			"forge": "FALL_VARIANTS",
			"fabric": "FALL_VARIANTS"
		},
		{
			"forge": "INTENTIONAL_GAME_DESIGN",
			"fabric": "INTENTIONAL_GAME_DESIGN"
		},
		{
			"forge": "CODEC",
			"fabric": "CODEC"
		},
		{
			"forge": "CODEC",
			"fabric": "CODEC"
		},
		{
			"forge": "id",
			"fabric": "id"
		},
		{
			"forge": "getSerializedName()",
			"fabric": "asString()"
		},
		{
			"forge": "getSerializedName()",
			"fabric": "asString()"
		}
	]
}