{
	"title": "net.minecraft.data.models.blockstates.PropertyDispatch$C3",
	"items": [
		{
			"forge": "net.minecraft.data.models.blockstates.PropertyDispatch$C3",
			"fabric": "net.minecraft.data.client.BlockStateVariantMap$TripleProperty"
		},
		{
			"forge": "property1",
			"fabric": "first"
		},
		{
			"forge": "property1",
			"fabric": "first"
		},
		{
			"forge": "property2",
			"fabric": "second"
		},
		{
			"forge": "property3",
			"fabric": "third"
		},
		{
			"forge": "getDefinedProperties()",
			"fabric": "getProperties()"
		},
		{
			"forge": "getDefinedProperties()",
			"fabric": "getProperties()"
		},
		{
			"forge": "select(T1 arg0, T2 arg1, T3 arg2, List<Variant> arg3)",
			"fabric": "register(T1 firstValue, T2 secondValue, T3 thirdValue, List<BlockStateVariant> variants)"
		},
		{
			"forge": "select(T1 arg0, T2 arg1, T3 arg2, Variant arg3)",
			"fabric": "register(T1 firstValue, T2 secondValue, T3 thirdValue, BlockStateVariant variant)"
		},
		{
			"forge": "generate(PropertyDispatch$TriFunction<T1, T2, T3, Variant> arg0)",
			"fabric": "register(BlockStateVariantMap$TriFunction<T1, T2, T3, BlockStateVariant> variantFactory)"
		},
		{
			"forge": "generateList(PropertyDispatch$TriFunction<T1, T2, T3, List<Variant>> arg0)",
			"fabric": "registerVariants(BlockStateVariantMap$TriFunction<T1, T2, T3, List<BlockStateVariant>> variantFactory)"
		}
	]
}