{
	"title": "com.mojang.realmsclient.dto.RealmsServerPlayerList",
	"items": [
		{
			"forge": "com.mojang.realmsclient.dto.RealmsServerPlayerList",
			"fabric": "net.minecraft.client.realms.dto.RealmsServerPlayerList"
		},
		{
			"forge": "LOGGER",
			"fabric": "LOGGER"
		},
		{
			"forge": "LOGGER",
			"fabric": "LOGGER"
		},
		{
			"forge": "JSON_PARSER",
			"fabric": "JSON_PARSER"
		},
		{
			"forge": "serverId",
			"fabric": "serverId"
		},
		{
			"forge": "players",
			"fabric": "players"
		},
		{
			"forge": "parse(com.google.gson.JsonObject arg0)",
			"fabric": "parse(com.google.gson.JsonObject node)"
		},
		{
			"forge": "parse(com.google.gson.JsonObject arg0)",
			"fabric": "parse(com.google.gson.JsonObject node)"
		},
		{
			"forge": "parsePlayers(com.google.gson.JsonArray arg0)",
			"fabric": "parsePlayers(com.google.gson.JsonArray jsonArray)"
		}
	]
}