{
	"title": "net.minecraft.world.entity.ai.behavior.BabyFollowAdult",
	"items": [
		{
			"forge": "net.minecraft.world.entity.ai.behavior.BabyFollowAdult",
			"fabric": "net.minecraft.entity.ai.brain.task.WalkTowardClosestAdultTask"
		},
		{
			"forge": "create(UniformInt arg0, float arg1)",
			"fabric": "create(UniformIntProvider executionRange, float speed)"
		},
		{
			"forge": "create(UniformInt arg0, float arg1)",
			"fabric": "create(UniformIntProvider executionRange, float speed)"
		},
		{
			"forge": "create(UniformInt arg0, Function<LivingEntity, Float> arg1)",
			"fabric": "create(UniformIntProvider executionRange, Function<LivingEntity, Float> speed)"
		}
	]
}