{
	"title": "com.mojang.realmsclient.util.task.DownloadTask",
	"items": [
		{
			"forge": "com.mojang.realmsclient.util.task.DownloadTask",
			"fabric": "net.minecraft.client.realms.task.DownloadTask"
		},
		{
			"forge": "LOGGER",
			"fabric": "LOGGER"
		},
		{
			"forge": "LOGGER",
			"fabric": "LOGGER"
		},
		{
			"forge": "worldId",
			"fabric": "worldId"
		},
		{
			"forge": "slot",
			"fabric": "slot"
		},
		{
			"forge": "lastScreen",
			"fabric": "lastScreen"
		},
		{
			"forge": "downloadName",
			"fabric": "downloadName"
		}
	]
}