{
	"title": "com.mojang.blaze3d.platform.Lighting",
	"items": [
		{
			"forge": "com.mojang.blaze3d.platform.Lighting",
			"fabric": "net.minecraft.client.render.DiffuseLighting"
		},
		{
			"forge": "DIFFUSE_LIGHT_0",
			"fabric": "field_24426"
		},
		{
			"forge": "DIFFUSE_LIGHT_0",
			"fabric": "field_24426"
		},
		{
			"forge": "DIFFUSE_LIGHT_1",
			"fabric": "field_24427"
		},
		{
			"forge": "NETHER_DIFFUSE_LIGHT_0",
			"fabric": "field_24428"
		},
		{
			"forge": "NETHER_DIFFUSE_LIGHT_1",
			"fabric": "field_24429"
		},
		{
			"forge": "INVENTORY_DIFFUSE_LIGHT_0",
			"fabric": "field_29567"
		},
		{
			"forge": "INVENTORY_DIFFUSE_LIGHT_1",
			"fabric": "field_29568"
		},
		{
			"forge": "setupNetherLevel(org.joml.Matrix4f arg0)",
			"fabric": "enableForLevel(org.joml.Matrix4f positionMatrix)"
		},
		{
			"forge": "setupNetherLevel(org.joml.Matrix4f arg0)",
			"fabric": "enableForLevel(org.joml.Matrix4f positionMatrix)"
		},
		{
			"forge": "setupLevel(org.joml.Matrix4f arg0)",
			"fabric": "disableForLevel(org.joml.Matrix4f positionMatrix)"
		},
		{
			"forge": "setupForFlatItems()",
			"fabric": "disableGuiDepthLighting()"
		},
		{
			"forge": "setupFor3DItems()",
			"fabric": "enableGuiDepthLighting()"
		},
		{
			"forge": "setupForEntityInInventory()",
			"fabric": "method_34742()"
		}
	]
}