{
	"title": "net.minecraft.world.level.block.WallTorchBlock",
	"items": [
		{
			"forge": "net.minecraft.world.level.block.WallTorchBlock",
			"fabric": "net.minecraft.block.WallTorchBlock"
		},
		{
			"forge": "FACING",
			"fabric": "FACING"
		},
		{
			"forge": "FACING",
			"fabric": "FACING"
		},
		{
			"forge": "AABB_OFFSET",
			"fabric": "field_31285"
		},
		{
			"forge": "AABBS",
			"fabric": "BOUNDING_SHAPES"
		},
		{
			"forge": "getDescriptionId()",
			"fabric": "getTranslationKey()"
		},
		{
			"forge": "getDescriptionId()",
			"fabric": "getTranslationKey()"
		},
		{
			"forge": "getShape(BlockState arg0, BlockGetter arg1, BlockPos arg2, CollisionContext arg3)",
			"fabric": "getOutlineShape(BlockState arg0, BlockView arg1, BlockPos arg2, ShapeContext arg3)"
		},
		{
			"forge": "getShape(BlockState arg0)",
			"fabric": "getBoundingShape(BlockState state)"
		},
		{
			"forge": "canSurvive(BlockState arg0, LevelReader arg1, BlockPos arg2)",
			"fabric": "canPlaceAt(BlockState arg0, WorldView arg1, BlockPos arg2)"
		},
		{
			"forge": "getStateForPlacement(BlockPlaceContext arg0)",
			"fabric": "getPlacementState(ItemPlacementContext arg0)"
		},
		{
			"forge": "updateShape(BlockState arg0, Direction arg1, BlockState arg2, LevelAccessor arg3, BlockPos arg4, BlockPos arg5)",
			"fabric": "getStateForNeighborUpdate(BlockState arg0, Direction arg1, BlockState arg2, WorldAccess arg3, BlockPos arg4, BlockPos arg5)"
		},
		{
			"forge": "animateTick(BlockState arg0, Level arg1, BlockPos arg2, RandomSource arg3)",
			"fabric": "randomDisplayTick(BlockState arg0, World arg1, BlockPos arg2, Random arg3)"
		},
		{
			"forge": "rotate(BlockState arg0, Rotation arg1)",
			"fabric": "rotate(BlockState arg0, BlockRotation arg1)"
		},
		{
			"forge": "mirror(BlockState arg0, Mirror arg1)",
			"fabric": "mirror(BlockState arg0, BlockMirror arg1)"
		},
		{
			"forge": "createBlockStateDefinition(StateDefinition$Builder<Block, BlockState> arg0)",
			"fabric": "appendProperties(StateManager$Builder<Block, BlockState> arg0)"
		}
	]
}