{
	"title": "net.minecraft.client.gui.screens.OptionsScreen",
	"items": [
		{
			"forge": "net.minecraft.client.gui.screens.OptionsScreen",
			"fabric": "net.minecraft.client.gui.screen.option.OptionsScreen"
		},
		{
			"forge": "SKIN_CUSTOMIZATION",
			"fabric": "SKIN_CUSTOMIZATION_TEXT"
		},
		{
			"forge": "SKIN_CUSTOMIZATION",
			"fabric": "SKIN_CUSTOMIZATION_TEXT"
		},
		{
			"forge": "SOUNDS",
			"fabric": "SOUNDS_TEXT"
		},
		{
			"forge": "VIDEO",
			"fabric": "VIDEO_TEXT"
		},
		{
			"forge": "CONTROLS",
			"fabric": "CONTROL_TEXT"
		},
		{
			"forge": "LANGUAGE",
			"fabric": "LANGUAGE_TEXT"
		},
		{
			"forge": "CHAT",
			"fabric": "CHAT_TEXT"
		},
		{
			"forge": "RESOURCEPACK",
			"fabric": "RESOURCE_PACK_TEXT"
		},
		{
			"forge": "ACCESSIBILITY",
			"fabric": "ACCESSIBILITY_TEXT"
		},
		{
			"forge": "TELEMETRY",
			"fabric": "TELEMETRY_TEXT"
		},
		{
			"forge": "CREDITS_AND_ATTRIBUTION",
			"fabric": "CREDITS_AND_ATTRIBUTION_TEXT"
		},
		{
			"forge": "COLUMNS",
			"fabric": "COLUMNS"
		},
		{
			"forge": "lastScreen",
			"fabric": "parent"
		},
		{
			"forge": "options",
			"fabric": "settings"
		},
		{
			"forge": "difficultyButton",
			"fabric": "difficultyButton"
		},
		{
			"forge": "lockButton",
			"fabric": "lockDifficultyButton"
		},
		{
			"forge": "init()",
			"fabric": "init()"
		},
		{
			"forge": "init()",
			"fabric": "init()"
		},
		{
			"forge": "applyPacks(PackRepository arg0)",
			"fabric": "refreshResourcePacks(ResourcePackManager resourcePackManager)"
		},
		{
			"forge": "createOnlineButton()",
			"fabric": "createTopRightButton()"
		},
		{
			"forge": "createDifficultyButton(int arg0, int arg1, String arg2, Minecraft arg3)",
			"fabric": "createDifficultyButtonWidget(int x, int y, String translationKey, MinecraftClient client)"
		},
		{
			"forge": "lockCallback(boolean arg0)",
			"fabric": "lockDifficulty(boolean difficultyLocked)"
		},
		{
			"forge": "removed()",
			"fabric": "removed()"
		},
		{
			"forge": "render(GuiGraphics arg0, int arg1, int arg2, float arg3)",
			"fabric": "render(DrawContext arg0, int arg1, int arg2, float arg3)"
		},
		{
			"forge": "openScreenButton(Component arg0, Supplier<Screen> arg1)",
			"fabric": "createButton(Text message, Supplier<Screen> screenSupplier)"
		}
	]
}