{
	"title": "net.minecraft.core.UUIDUtil",
	"items": [
		{
			"forge": "net.minecraft.core.UUIDUtil",
			"fabric": "net.minecraft.util.Uuids"
		},
		{
			"forge": "CODEC",
			"fabric": "INT_STREAM_CODEC"
		},
		{
			"forge": "CODEC",
			"fabric": "INT_STREAM_CODEC"
		},
		{
			"forge": "STRING_CODEC",
			"fabric": "STRING_CODEC"
		},
		{
			"forge": "AUTHLIB_CODEC",
			"fabric": "CODEC"
		},
		{
			"forge": "UUID_BYTES",
			"fabric": "BYTE_ARRAY_SIZE"
		},
		{
			"forge": "UUID_PREFIX_OFFLINE_PLAYER",
			"fabric": "OFFLINE_PLAYER_UUID_PREFIX"
		},
		{
			"forge": "uuidFromIntArray(int[] arg0)",
			"fabric": "toUuid(int[] array)"
		},
		{
			"forge": "uuidFromIntArray(int[] arg0)",
			"fabric": "toUuid(int[] array)"
		},
		{
			"forge": "uuidToIntArray(UUID arg0)",
			"fabric": "toIntArray(UUID uuid)"
		},
		{
			"forge": "leastMostToIntArray(long arg0, long arg1)",
			"fabric": "toIntArray(long uuidMost, long uuidLeast)"
		},
		{
			"forge": "uuidToByteArray(UUID arg0)",
			"fabric": "toByteArray(UUID uuid)"
		},
		{
			"forge": "readUUID(com.mojang.serialization.Dynamic<?> arg0)",
			"fabric": "toUuid(com.mojang.serialization.Dynamic<?> dynamic)"
		},
		{
			"forge": "getOrCreatePlayerUUID(com.mojang.authlib.GameProfile arg0)",
			"fabric": "getUuidFromProfile(com.mojang.authlib.GameProfile profile)"
		},
		{
			"forge": "createOfflinePlayerUUID(String arg0)",
			"fabric": "getOfflinePlayerUuid(String nickname)"
		}
	]
}