{
	"title": "net.minecraft.world.level.storage.loot.functions.SetInstrumentFunction$Serializer",
	"items": [
		{
			"forge": "net.minecraft.world.level.storage.loot.functions.SetInstrumentFunction$Serializer",
			"fabric": "net.minecraft.loot.function.SetInstrumentLootFunction$Serializer"
		},
		{
			"forge": "serialize(com.google.gson.JsonObject arg0, SetInstrumentFunction arg1, com.google.gson.JsonSerializationContext arg2)",
			"fabric": "toJson(com.google.gson.JsonObject arg0, SetInstrumentLootFunction arg1, com.google.gson.JsonSerializationContext arg2)"
		},
		{
			"forge": "serialize(com.google.gson.JsonObject arg0, SetInstrumentFunction arg1, com.google.gson.JsonSerializationContext arg2)",
			"fabric": "toJson(com.google.gson.JsonObject arg0, SetInstrumentLootFunction arg1, com.google.gson.JsonSerializationContext arg2)"
		},
		{
			"forge": "deserialize(com.google.gson.JsonObject arg0, com.google.gson.JsonDeserializationContext arg1, LootItemCondition[] arg2)",
			"fabric": "fromJson(com.google.gson.JsonObject arg0, com.google.gson.JsonDeserializationContext arg1, LootCondition[] arg2)"
		}
	]
}