{
	"title": "net.minecraft.client.renderer.entity.RabbitRenderer",
	"items": [
		{
			"forge": "net.minecraft.client.renderer.entity.RabbitRenderer",
			"fabric": "net.minecraft.client.render.entity.RabbitEntityRenderer"
		},
		{
			"forge": "RABBIT_BROWN_LOCATION",
			"fabric": "BROWN_TEXTURE"
		},
		{
			"forge": "RABBIT_BROWN_LOCATION",
			"fabric": "BROWN_TEXTURE"
		},
		{
			"forge": "RABBIT_WHITE_LOCATION",
			"fabric": "WHITE_TEXTURE"
		},
		{
			"forge": "RABBIT_BLACK_LOCATION",
			"fabric": "BLACK_TEXTURE"
		},
		{
			"forge": "RABBIT_GOLD_LOCATION",
			"fabric": "GOLD_TEXTURE"
		},
		{
			"forge": "RABBIT_SALT_LOCATION",
			"fabric": "SALT_TEXTURE"
		},
		{
			"forge": "RABBIT_WHITE_SPLOTCHED_LOCATION",
			"fabric": "WHITE_SPLOTCHED_TEXTURE"
		},
		{
			"forge": "RABBIT_TOAST_LOCATION",
			"fabric": "TOAST_TEXTURE"
		},
		{
			"forge": "RABBIT_EVIL_LOCATION",
			"fabric": "CAERBANNOG_TEXTURE"
		},
		{
			"forge": "getTextureLocation(Rabbit arg0)",
			"fabric": "getTexture(RabbitEntity arg0)"
		},
		{
			"forge": "getTextureLocation(Rabbit arg0)",
			"fabric": "getTexture(RabbitEntity arg0)"
		}
	]
}